[
    {
        "id_kereta": "KA001",
        "tanggal": "2025-03-29",
        "gerbong": [
            {
                "id_gerbong": "KA001-G1",
                "kapasitas": 80,
                "kursi": {
                    "A1": true,
                    "B1": true,
                    "C1": true,
                    "D1": true,
                    "A2": true,
                    "B2": true,
                    "C2": true,
                    "D2": true,
                    "A3": true,
                    "B3": true,
                    "C3": true,
                    "D3": true,
                    "A4": true,
                    "B4": true,
                    "C4": true,
                    "D4": true,
                    "A5": true,
                    "B5": true,
                    "C5": true,
                    "D5": true,
                    "A6": true,
                    "B6": true,
                    "C6": true,
                    "D6": true,
                    "A7": true,
                    "B7": true,
                    "C7": true,
                    "D7": true,
                    "A8": true,
                    "B8": true,
                    "C8": true,
                    "D8": true,
                    "A9": true,
                    "B9": true,
                    "C9": true,
                    "D9": true,
                    "A10": true,
                    "B10": true,
                    "C10": true,
                    "D10": true,
                    "A11": true,
                    "B11": true,
                    "C11": true,
                    "D11": true,
                    "A12": true,
                    "B12": true,
                    "C12": true,
                    "D12": true,
                    "A13": true,
                    "B13": true,
                    "C13": true,
                    "D13": true,
                    "A14": true,
                    "B14": true,
                    "C14": true,
                    "D14": true,
                    "A15": true,
                    "B15": true,
                    "C15": true,
                    "D15": true,
                    "A16": true,
                    "B16": true,
                    "C16": true,
                    "D16": true,
                    "A17": true,
                    "B17": true,
                    "C17": true,
                    "D17": true,
                    "A18": true,
                    "B18": true,
                    "C18": true,
                    "D18": true,
                    "A19": true,
                    "B19": true,
                    "C19": true,
                    "D19": true,
                    "A20": true,
                    "B20": true,
                    "C20": true,
                    "D20": true
                }
            },
            {
                "id_gerbong": "KA001-G2",
                "kapasitas": 80,
                "kursi": {
                    "A1": true,
                    "B1": true,
                    "C1": true,
                    "D1": true,
                    "A2": true,
                    "B2": true,
                    "C2": true,
                    "D2": true,
                    "A3": true,
                    "B3": true,
                    "C3": true,
                    "D3": true,
                    "A4": true,
                    "B4": true,
                    "C4": true,
                    "D4": true,
                    "A5": true,
                    "B5": true,
                    "C5": true,
                    "D5": true,
                    "A6": true,
                    "B6": true,
                    "C6": true,
                    "D6": true,
                    "A7": true,
                    "B7": true,
                    "C7": true,
                    "D7": true,
                    "A8": true,
                    "B8": true,
                    "C8": true,
                    "D8": true,
                    "A9": true,
                    "B9": true,
                    "C9": true,
                    "D9": true,
                    "A10": true,
                    "B10": true,
                    "C10": true,
                    "D10": true,
                    "A11": true,
                    "B11": true,
                    "C11": true,
                    "D11": true,
                    "A12": true,
                    "B12": true,
                    "C12": true,
                    "D12": true,
                    "A13": true,
                    "B13": true,
                    "C13": true,
                    "D13": true,
                    "A14": true,
                    "B14": true,
                    "C14": true,
                    "D14": true,
                    "A15": true,
                    "B15": true,
                    "C15": true,
                    "D15": true,
                    "A16": true,
                    "B16": true,
                    "C16": true,
                    "D16": true,
                    "A17": true,
                    "B17": true,
                    "C17": true,
                    "D17": true,
                    "A18": true,
                    "B18": true,
                    "C18": true,
                    "D18": true,
                    "A19": true,
                    "B19": true,
                    "C19": true,
                    "D19": true,
                    "A20": true,
                    "B20": true,
                    "C20": true,
                    "D20": true
                }
            },
            {
                "id_gerbong": "KA001-G3",
                "kapasitas": 80,
                "kursi": {
                    "A1": true,
                    "B1": true,
                    "C1": true,
                    "D1": true,
                    "A2": true,
                    "B2": true,
                    "C2": true,
                    "D2": true,
                    "A3": true,
                    "B3": true,
                    "C3": true,
                    "D3": true,
                    "A4": true,
                    "B4": true,
                    "C4": true,
                    "D4": true,
                    "A5": true,
                    "B5": true,
                    "C5": true,
                    "D5": true,
                    "A6": true,
                    "B6": true,
                    "C6": true,
                    "D6": true,
                    "A7": true,
                    "B7": true,
                    "C7": true,
                    "D7": true,
                    "A8": true,
                    "B8": true,
                    "C8": true,
                    "D8": true,
                    "A9": true,
                    "B9": true,
                    "C9": true,
                    "D9": true,
                    "A10": true,
                    "B10": true,
                    "C10": true,
                    "D10": true,
                    "A11": true,
                    "B11": true,
                    "C11": true,
                    "D11": true,
                    "A12": true,
                    "B12": true,
                    "C12": true,
                    "D12": true,
                    "A13": true,
                    "B13": true,
                    "C13": true,
                    "D13": true,
                    "A14": true,
                    "B14": true,
                    "C14": true,
                    "D14": true,
                    "A15": true,
                    "B15": true,
                    "C15": true,
                    "D15": true,
                    "A16": true,
                    "B16": true,
                    "C16": true,
                    "D16": true,
                    "A17": true,
                    "B17": true,
                    "C17": true,
                    "D17": true,
                    "A18": true,
                    "B18": true,
                    "C18": true,
                    "D18": true,
                    "A19": true,
                    "B19": true,
                    "C19": true,
                    "D19": true,
                    "A20": true,
                    "B20": true,
                    "C20": true,
                    "D20": true
                }
            },
            {
                "id_gerbong": "KA001-G4",
                "kapasitas": 80,
                "kursi": {
                    "A1": true,
                    "B1": true,
                    "C1": true,
                    "D1": true,
                    "A2": true,
                    "B2": true,
                    "C2": true,
                    "D2": true,
                    "A3": true,
                    "B3": true,
                    "C3": true,
                    "D3": true,
                    "A4": true,
                    "B4": true,
                    "C4": true,
                    "D4": true,
                    "A5": true,
                    "B5": true,
                    "C5": true,
                    "D5": true,
                    "A6": true,
                    "B6": true,
                    "C6": true,
                    "D6": true,
                    "A7": true,
                    "B7": true,
                    "C7": true,
                    "D7": true,
                    "A8": true,
                    "B8": true,
                    "C8": true,
                    "D8": true,
                    "A9": true,
                    "B9": true,
                    "C9": true,
                    "D9": true,
                    "A10": true,
                    "B10": true,
                    "C10": true,
                    "D10": true,
                    "A11": true,
                    "B11": true,
                    "C11": true,
                    "D11": true,
                    "A12": true,
                    "B12": true,
                    "C12": true,
                    "D12": true,
                    "A13": true,
                    "B13": true,
                    "C13": true,
                    "D13": true,
                    "A14": true,
                    "B14": true,
                    "C14": true,
                    "D14": true,
                    "A15": true,
                    "B15": true,
                    "C15": true,
                    "D15": true,
                    "A16": true,
                    "B16": true,
                    "C16": true,
                    "D16": true,
                    "A17": true,
                    "B17": true,
                    "C17": true,
                    "D17": true,
                    "A18": true,
                    "B18": true,
                    "C18": true,
                    "D18": true,
                    "A19": true,
                    "B19": true,
                    "C19": true,
                    "D19": true,
                    "A20": true,
                    "B20": true,
                    "C20": true,
                    "D20": true
                }
            }
        ]
    },
    {
        "id_kereta": "KA002",
        "tanggal": "2025-05-01",
        "gerbong": [
            {
                "id_gerbong": "KA002-G1",
                "kapasitas": 52,
                "kursi": {
                    "A1": true,
                    "B1": true,
                    "C1": true,
                    "D1": true,
                    "A2": true,
                    "B2": true,
                    "C2": true,
                    "D2": true,
                    "A3": true,
                    "B3": true,
                    "C3": true,
                    "D3": true,
                    "A4": true,
                    "B4": true,
                    "C4": true,
                    "D4": true,
                    "A5": true,
                    "B5": true,
                    "C5": true,
                    "D5": true,
                    "A6": true,
                    "B6": true,
                    "C6": true,
                    "D6": true,
                    "A7": true,
                    "B7": true,
                    "C7": true,
                    "D7": true,
                    "A8": true,
                    "B8": true,
                    "C8": true,
                    "D8": true,
                    "A9": true,
                    "B9": true,
                    "C9": true,
                    "D9": true,
                    "A10": true,
                    "B10": true,
                    "C10": true,
                    "D10": true,
                    "A11": true,
                    "B11": true,
                    "C11": true,
                    "D11": true,
                    "A12": true,
                    "B12": true,
                    "C12": true,
                    "D12": true,
                    "A13": true,
                    "B13": true,
                    "C13": true,
                    "D13": true
                }
            },
            {
                "id_gerbong": "KA002-G2",
                "kapasitas": 52,
                "kursi": {
                    "A1": true,
                    "B1": true,
                    "C1": true,
                    "D1": true,
                    "A2": true,
                    "B2": true,
                    "C2": true,
                    "D2": true,
                    "A3": true,
                    "B3": true,
                    "C3": true,
                    "D3": true,
                    "A4": true,
                    "B4": true,
                    "C4": true,
                    "D4": true,
                    "A5": true,
                    "B5": true,
                    "C5": true,
                    "D5": true,
                    "A6": true,
                    "B6": true,
                    "C6": true,
                    "D6": true,
                    "A7": true,
                    "B7": true,
                    "C7": true,
                    "D7": true,
                    "A8": true,
                    "B8": true,
                    "C8": true,
                    "D8": true,
                    "A9": true,
                    "B9": true,
                    "C9": true,
                    "D9": true,
                    "A10": true,
                    "B10": true,
                    "C10": true,
                    "D10": true,
                    "A11": true,
                    "B11": true,
                    "C11": true,
                    "D11": true,
                    "A12": true,
                    "B12": true,
                    "C12": true,
                    "D12": true,
                    "A13": true,
                    "B13": true,
                    "C13": true,
                    "D13": true
                }
            },
            {
                "id_gerbong": "KA002-G3",
                "kapasitas": 52,
                "kursi": {
                    "A1": true,
                    "B1": true,
                    "C1": true,
                    "D1": true,
                    "A2": true,
                    "B2": true,
                    "C2": true,
                    "D2": true,
                    "A3": true,
                    "B3": true,
                    "C3": true,
                    "D3": true,
                    "A4": true,
                    "B4": true,
                    "C4": true,
                    "D4": true,
                    "A5": true,
                    "B5": true,
                    "C5": true,
                    "D5": true,
                    "A6": true,
                    "B6": true,
                    "C6": true,
                    "D6": true,
                    "A7": true,
                    "B7": true,
                    "C7": true,
                    "D7": true,
                    "A8": true,
                    "B8": true,
                    "C8": true,
                    "D8": true,
                    "A9": true,
                    "B9": true,
                    "C9": true,
                    "D9": true,
                    "A10": true,
                    "B10": true,
                    "C10": true,
                    "D10": true,
                    "A11": true,
                    "B11": true,
                    "C11": true,
                    "D11": true,
                    "A12": true,
                    "B12": true,
                    "C12": true,
                    "D12": true,
                    "A13": true,
                    "B13": true,
                    "C13": true,
                    "D13": true
                }
            },
            {
                "id_gerbong": "KA002-G4",
                "kapasitas": 52,
                "kursi": {
                    "A1": true,
                    "B1": true,
                    "C1": true,
                    "D1": true,
                    "A2": true,
                    "B2": true,
                    "C2": true,
                    "D2": true,
                    "A3": true,
                    "B3": true,
                    "C3": true,
                    "D3": true,
                    "A4": true,
                    "B4": true,
                    "C4": true,
                    "D4": true,
                    "A5": true,
                    "B5": true,
                    "C5": true,
                    "D5": true,
                    "A6": true,
                    "B6": true,
                    "C6": true,
                    "D6": true,
                    "A7": true,
                    "B7": true,
                    "C7": true,
                    "D7": true,
                    "A8": true,
                    "B8": true,
                    "C8": true,
                    "D8": true,
                    "A9": true,
                    "B9": true,
                    "C9": true,
                    "D9": true,
                    "A10": true,
                    "B10": true,
                    "C10": true,
                    "D10": true,
                    "A11": true,
                    "B11": true,
                    "C11": true,
                    "D11": true,
                    "A12": true,
                    "B12": true,
                    "C12": true,
                    "D12": true,
                    "A13": true,
                    "B13": true,
                    "C13": true,
                    "D13": true
                }
            }
        ]
    },
    {
        "id_kereta": "KA003",
        "tanggal": "2025-05-05",
        "gerbong": [
            {
                "id_gerbong": "KA003-G1",
                "kapasitas": 52,
                "kursi": {
                    "A1": true,
                    "B1": true,
                    "C1": true,
                    "D1": true,
                    "A2": true,
                    "B2": true,
                    "C2": true,
                    "D2": true,
                    "A3": true,
                    "B3": true,
                    "C3": true,
                    "D3": true,
                    "A4": true,
                    "B4": true,
                    "C4": true,
                    "D4": true,
                    "A5": true,
                    "B5": true,
                    "C5": true,
                    "D5": true,
                    "A6": true,
                    "B6": true,
                    "C6": true,
                    "D6": true,
                    "A7": true,
                    "B7": true,
                    "C7": true,
                    "D7": true,
                    "A8": true,
                    "B8": true,
                    "C8": true,
                    "D8": true,
                    "A9": true,
                    "B9": true,
                    "C9": true,
                    "D9": true,
                    "A10": true,
                    "B10": true,
                    "C10": true,
                    "D10": true,
                    "A11": true,
                    "B11": true,
                    "C11": true,
                    "D11": true,
                    "A12": true,
                    "B12": true,
                    "C12": true,
                    "D12": true,
                    "A13": true,
                    "B13": true,
                    "C13": true,
                    "D13": true
                }
            },
            {
                "id_gerbong": "KA003-G2",
                "kapasitas": 52,
                "kursi": {
                    "A1": true,
                    "B1": true,
                    "C1": true,
                    "D1": true,
                    "A2": true,
                    "B2": true,
                    "C2": true,
                    "D2": true,
                    "A3": true,
                    "B3": true,
                    "C3": true,
                    "D3": true,
                    "A4": true,
                    "B4": true,
                    "C4": true,
                    "D4": true,
                    "A5": true,
                    "B5": true,
                    "C5": true,
                    "D5": true,
                    "A6": true,
                    "B6": true,
                    "C6": true,
                    "D6": true,
                    "A7": true,
                    "B7": true,
                    "C7": true,
                    "D7": true,
                    "A8": true,
                    "B8": true,
                    "C8": true,
                    "D8": true,
                    "A9": true,
                    "B9": true,
                    "C9": true,
                    "D9": true,
                    "A10": true,
                    "B10": true,
                    "C10": true,
                    "D10": true,
                    "A11": true,
                    "B11": true,
                    "C11": true,
                    "D11": true,
                    "A12": true,
                    "B12": true,
                    "C12": true,
                    "D12": true,
                    "A13": true,
                    "B13": true,
                    "C13": true,
                    "D13": true
                }
            },
            {
                "id_gerbog": "KA003-G3",
                "kapasitas": 52,
                "kursi": {
                    "A1": true,
                    "B1": true,
                    "C1": true,
                    "D1": true,
                    "A2": true,
                    "B2": true,
                    "C2": true,
                    "D2": true,
                    "A3": true,
                    "B3": true,
                    "C3": true,
                    "D3": true,
                    "A4": true,
                    "B4": true,
                    "C4": true,
                    "D4": true,
                    "A5": true,
                    "B5": true,
                    "C5": true,
                    "D5": true,
                    "A6": true,
                    "B6": true,
                    "C6": true,
                    "D6": true,
                    "A7": true,
                    "B7": true,
                    "C7": true,
                    "D7": true,
                    "A8": true,
                    "B8": true,
                    "C8": true,
                    "D8": true,
                    "A9": true,
                    "B9": true,
                    "C9": true,
                    "D9": true,
                    "A10": true,
                    "B10": true,
                    "C10": true,
                    "D10": true,
                    "A11": true,
                    "B11": true,
                    "C11": true,
                    "D11": true,
                    "A12": true,
                    "B12": true,
                    "C12": true,
                    "D12": true,
                    "A13": true,
                    "B13": true,
                    "C13": true,
                    "D13": true
                }
            }
        ]
    }
]
